lctutil/__init__.py
lctutil/ac_matcher.py
lctutil/extract_base_info.py
lctutil/openai.py
lctutil/stock_infos.py
lctutil/zhipuai.py
lctutils/__init__.py
lctutils/ac_matcher.py
lctutils/extract_base_info.py
lctutils/openai.py
lctutils/stock_infos.py
req_utils/__init__.py
req_utils/opt_openai.py
stock_infos/__init__.py
stock_infos/ac_matcher.py
stock_infos/base_infos.py
stock_infos/extract_base_info.py
lctutil-0.9.0.dist-info/METADATA
lctutil-0.9.0.dist-info/WHEEL
lctutil-0.9.0.dist-info/top_level.txt
lctutil-0.9.0.dist-info/RECORD
