Metadata-Version: 2.1
Name: lctutil
Version: 0.9.0
Summary: LCT utils
Home-page: https://github.com/yourusername/mypackage
Author: LCT
Author-email: your.email@example.com
Classifier: Programming Language :: Python :: 3
Classifier: License :: OSI Approved :: MIT License
Classifier: Operating System :: OS Independent
Requires-Dist: pyahocorasick
Requires-Dist: openai
Requires-Dist: tenacity
Requires-Dist: requests[socks]
Requires-Dist: zhipuai
